scriputils/__init__.py
scriputils/constants.py
scriputils/timer.py
scriputils/utils.py
scriputils-0.2.6.dist-info/LICENSE
scriputils-0.2.6.dist-info/METADATA
scriputils-0.2.6.dist-info/WHEEL
scriputils-0.2.6.dist-info/RECORD
