Metadata-Version: 2.1
Name: scriputils
Version: 0.2.6
Summary: An essential utility library for Python scripts, offering robust functions for reading YAML configurations, initializing loggers, and parsing command-line arguments.
License: MIT
Author: donaId
Author-email: simonovyup@gmail.com
Requires-Python: >=3.9,<4.0
Classifier: License :: OSI Approved :: MIT License
Classifier: Programming Language :: Python :: 3
Classifier: Programming Language :: Python :: 3.9
Classifier: Programming Language :: Python :: 3.10
Classifier: Programming Language :: Python :: 3.11
Classifier: Programming Language :: Python :: 3.12
Classifier: Programming Language :: Python :: 3.13
Requires-Dist: pyyaml (>=6.0.2,<7.0.0)
Requires-Dist: setuptools (>=70.1.1)
